robot_motion_program_opt/__init__.py
robot_motion_program_opt/cmd_gen/__init__.py
robot_motion_program_opt/cmd_gen/cmd_gen.py
robot_motion_program_opt/cmd_gen/fitting_toolbox.py
robot_motion_program_opt/cmd_gen/fitting_toolbox_dual.py
robot_motion_program_opt/cmd_gen/greedy.py
robot_motion_program_opt/cmd_gen/greedy_dual.py
robot_motion_program_opt/motion_update/__init__.py
robot_motion_program_opt/motion_update/ilc_toolbox.py
robot_motion_program_opt/motion_update/motion_update.py
robot_motion_program_opt/redundancy_resolution/__init__.py
robot_motion_program_opt/redundancy_resolution/baseline.py
robot_motion_program_opt/redundancy_resolution/constraint_solver.py
robot_motion_program_opt/redundancy_resolution/redundancy_resolution.py
robot_motion_program_opt/toolbox/__init__.py
robot_motion_program_opt/toolbox/abb_utils.py
robot_motion_program_opt/toolbox/blending.py
robot_motion_program_opt/toolbox/dual_arm.py
robot_motion_program_opt/toolbox/error_check.py
robot_motion_program_opt/toolbox/fanuc_utils.py
robot_motion_program_opt/toolbox/gazebo_model_resource_locator.py
robot_motion_program_opt/toolbox/lambda_calc.py
robot_motion_program_opt/toolbox/realrobot.py
robot_motion_program_opt/toolbox/robotraconteur_mp_utils.py
robot_motion_program_opt/toolbox/robots_def.py
robot_motion_program_opt/toolbox/tes_env.py
robot_motion_program_opt/toolbox/toolbox_circular_fit.py
robot_motion_program_opt/toolbox/utils.py
robot_motion_program_opt-0.0.1.dist-info/METADATA
robot_motion_program_opt-0.0.1.dist-info/WHEEL
robot_motion_program_opt-0.0.1.dist-info/top_level.txt
robot_motion_program_opt-0.0.1.dist-info/RECORD
